nest/__init__.py
nest/cli/__init__.py
nest/cli/cli.py
nest/cli/click_handlers.py
nest/cli/src/__init__.py
nest/cli/src/app_controller.py
nest/cli/src/app_module.py
nest/cli/src/app_service.py
nest/cli/src/generate/__init__.py
nest/cli/src/generate/generate_controller.py
nest/cli/src/generate/generate_model.py
nest/cli/src/generate/generate_module.py
nest/cli/src/generate/generate_service.py
nest/cli/templates/__init__.py
nest/cli/templates/abstract_empty_template.py
nest/cli/templates/base_template.py
nest/cli/templates/blank_template.py
nest/cli/templates/cli_templates.py
nest/cli/templates/mongo_db_template.py
nest/cli/templates/mongo_template.py
nest/cli/templates/mysql_template.py
nest/cli/templates/orm_template.py
nest/cli/templates/postgres_template.py
nest/cli/templates/relational_db_template.py
nest/cli/templates/sqlite_template.py
nest/cli/templates/templates_factory.py
nest/common/__init__.py
nest/common/constants.py
nest/common/exceptions.py
nest/common/module.py
nest/common/route_resolver.py
nest/core/__init__.py
nest/core/cli_factory.py
nest/core/database/__init__.py
nest/core/database/base_config.py
nest/core/database/odm_config.py
nest/core/database/odm_provider.py
nest/core/database/orm_config.py
nest/core/database/orm_provider.py
nest/core/decorators/__init__.py
nest/core/decorators/class_based_view.py
nest/core/decorators/cli/__init__.py
nest/core/decorators/cli/cli_decorators.py
nest/core/decorators/controller.py
nest/core/decorators/database.py
nest/core/decorators/guards.py
nest/core/decorators/http_code.py
nest/core/decorators/http_method.py
nest/core/decorators/injectable.py
nest/core/decorators/module.py
nest/core/decorators/utils.py
nest/core/pynest_app_context.py
nest/core/pynest_application.py
nest/core/pynest_container.py
nest/core/pynest_factory.py
pynest_api-0.4.0.dist-info/LICENSE
pynest_api-0.4.0.dist-info/METADATA
pynest_api-0.4.0.dist-info/WHEEL
pynest_api-0.4.0.dist-info/entry_points.txt
pynest_api-0.4.0.dist-info/RECORD
