Metadata-Version: 2.3
Name: pynest-api
Version: 0.4.0
Summary: PyNest is a FastAPI Abstraction for building microservices, influenced by NestJS.
Author: itay.dar
Author-email: itay.dar@lemonade.com
Requires-Python: >=3.9,<4.0
Classifier: Development Status :: 4 - Beta
Classifier: Intended Audience :: Developers
Classifier: License :: OSI Approved :: MIT License
Classifier: Operating System :: OS Independent
Classifier: Programming Language :: Python :: 3
Classifier: Programming Language :: Python :: 3.9
Classifier: Programming Language :: Python :: 3.10
Classifier: Programming Language :: Python :: 3.11
Classifier: Programming Language :: Python :: 3.12
Classifier: Programming Language :: Python :: 3.13
Classifier: Topic :: Software Development :: Libraries :: Python Modules
Provides-Extra: mongo
Provides-Extra: postgres
Provides-Extra: test
Requires-Dist: alembic (>=1.13.3,<2.0.0) ; extra == "postgres"
Requires-Dist: astor (>=0.8.1,<0.9.0)
Requires-Dist: asyncpg (>=0.30.0,<0.31.0) ; extra == "postgres"
Requires-Dist: beanie (>=1.27.0,<2.0.0) ; extra == "mongo"
Requires-Dist: black (>=24.10.0,<25.0.0)
Requires-Dist: click (>=8.1.7,<9.0.0)
Requires-Dist: fastapi (>=0.115.4,<0.116.0)
Requires-Dist: greenlet (>=3.1.1,<4.0.0) ; extra == "postgres"
Requires-Dist: injector (>=0.22.0,<0.23.0)
Requires-Dist: psycopg2 (>=2.9.3,<3.0.0) ; extra == "postgres"
Requires-Dist: pydantic (>=2.9.2,<3.0.0)
Requires-Dist: python-dotenv (>=1.0.1,<2.0.0) ; extra == "postgres" or extra == "mongo"
Requires-Dist: pyyaml (>=6.0.2,<7.0.0)
Requires-Dist: sqlalchemy (>=2.0.36,<3.0.0) ; extra == "postgres"
Requires-Dist: uvicorn (>=0.32.0,<0.33.0)
Project-URL: Documentation, https://pythonnest.github.io/PyNest/
Project-URL: Homepage, https://github.com/PythonNest/PyNest
